{"id": 98, "name": "Texte de la commission sur la proposition de loi, apr\u00e8s engagement de la proc\u00e9dure acc\u00e9l\u00e9r\u00e9e, de M. Harold Huwart et plusieurs de ses coll\u00e8gues de simplification du droit de l'urbanisme et du logement (1240)., n\u00b0\u00a01378-A0", "url": "/dyn/17/amendements/1378/AN/98", "date": "2025-05-12", "status": "Adopt\u00e9", "proposed_by": [{"first_name": "S\u00e9bastien", "last_name": "Huyghe", "party": "Ensemble pour la R\u00e9publique"}], "summary": "Depuis 2023, la r\u00e9glementation applicable aux b\u00e2timents neufs a accru la superficie des locaux d\u00e9di\u00e9s au stationnement des v\u00e9los pour accompagner le d\u00e9veloppement des mobilit\u00e9s douces. A titre d\u2019illustration, pour un logement neuf, la superficie d\u2019un emplacement de stationnement de v\u00e9lo est pass\u00e9e de 0.75m2 \u00e0 1.5m2.En pratique, le cumul des r\u00e8gles locales relatives au stationnement des v\u00e9hicules motoris\u00e9s et des v\u00e9los aboutit \u00e0 augmenter les surfaces d\u00e9di\u00e9es au stationnement dans les b\u00e2timents, au d\u00e9triment des surfaces commercialis\u00e9es et d\u00e9velopp\u00e9es pour l\u2019usage du b\u00e2timent (ex.\u00a0: surface habitable), entrainant une hausse du prix de vente des locaux concern\u00e9s.Pour tenir compte de cette \u00e9volution n\u00e9cessaire, des dispositions ont \u00e9t\u00e9 introduites dans le code de l\u2019urbanisme pour r\u00e9duire les stationnements d\u00e9di\u00e9s aux v\u00e9hicules en pr\u00e9sence de places pr\u00e9vues pour les v\u00e9los. Cependant, ces dispositions sont rest\u00e9es lettres mortes car d\u2019application facultative.Le pr\u00e9sent amendement vise \u00e0 supprimer ces dispositions facultatives pour pr\u00e9voir leur application de plein droit."}