{"id": 1613, "name": "Texte de la commission sur la proposition de loi de M. Olivier Falorni relative \u00e0 la fin de vie (1100)., n\u00b0\u00a01364-A0", "url": "/dyn/17/amendements/1364/AN/1613", "date": "2025-05-09", "status": "Rejet\u00e9", "proposed_by": [{"first_name": "Thibault", "last_name": "Bazin", "party": "Droite R\u00e9publicaine"}, {"first_name": "Philippe", "last_name": "Juvin", "party": "Droite R\u00e9publicaine"}, {"first_name": "Patrick", "last_name": "Hetzel", "party": "Droite R\u00e9publicaine"}, {"first_name": "Fabien", "last_name": "Di Filippo", "party": "Droite R\u00e9publicaine"}, {"first_name": "Justine", "last_name": "Gruet", "party": "Droite R\u00e9publicaine"}, {"first_name": "Xavier", "last_name": "Breton", "party": "Droite R\u00e9publicaine"}, {"first_name": "Philippe", "last_name": "Gosselin", "party": "Droite R\u00e9publicaine"}, {"first_name": "Nicolas", "last_name": "Ray", "party": "Droite R\u00e9publicaine"}], "summary": "Amendement de repli \u00e0 l'amendement n\u00b01052 Juvin.\nLes conditions d\u2019acc\u00e8s de l\u2019aide \u00e0 mourir sont fond\u00e9es sur des notions insuffisamment d\u00e9finies qui\u00a0peuvent donner lieu \u00e0 des d\u00e9rives.\nPour \u00e9viter toute d\u00e9rive il convient d\u2019exclure des conditions d\u2019acc\u00e8s \u00e0 l\u2019aide \u00e0 mourir les personnes\u00a0sous curatelle ou tutelle, \u00e9tant entendu que leur situation ne leur permet pas toujours de garantir l\u2019exercice de leur volont\u00e9 de mani\u00e8re libre et \u00e9clair\u00e9e."}