{"id": 1001, "name": "Projet de loi de finances pour 2025, n\u00b0\u00a0324", "url": "/dyn/17/amendements/0324A/AN/1001", "date": "2024-10-17", "status": "Adopt\u00e9", "proposed_by": [{"first_name": "K\u00e9vin", "last_name": "Mauvieux", "party": "Rassemblement National"}], "summary": "Les Obligations Assimilables du Tr\u00e9sor index\u00e9es sur l\u2019inflation (OATi) sont des titres de dette \u00e9mis par l\u2019\u00c9tat fran\u00e7ais, dont le principal est ajust\u00e9 en fonction de l\u2019inflation. Ces instruments financiers se r\u00e9v\u00e8lent co\u00fbteux pour les finances publiques. En effet, chaque hausse de l\u2019inflation entra\u00eene une augmentation du co\u00fbt de ces obligations pour le contribuable.\n\nEn 2023, le co\u00fbt de la charge de la dette des obligations index\u00e9es sur l\u2019inflation (OATi), en particulier celles \u00e9mises entre 2018 et 2020, a \u00e9t\u00e9 \u00e9lev\u00e9 en raison de l\u2019inflation. En 2022, les OATi avaient d\u00e9j\u00e0 engendr\u00e9 un surco\u00fbt de 15,5 milliards d\u2019euros pour l\u2019\u00c9tat fran\u00e7ais. Ce montant est li\u00e9 \u00e0 la forte hausse de l\u2019inflation qui a directement augment\u00e9 les montants d\u2019int\u00e9r\u00eats vers\u00e9s sur ces obligations. Pourtant, durant les ann\u00e9es comprises entre 2018 et 2020, les taux \u00e9taient n\u00e9gatifs, il \u00e9tait donc pr\u00e9visible que l\u2019inflation augmenterait dans les ann\u00e9es suivantes, ce qui aurait pu inciter \u00e0 privil\u00e9gier des \u00e9missions d\u2019obligations \u00e0 taux fixe, afin de minimiser la charge future de la dette publique. Une telle strat\u00e9gie peut \u00eatre per\u00e7ue comme une prise de risque excessive, ayant eu pour cons\u00e9quence d\u2019alourdir inutilement la charge de la dette publique.\n\nDe plus, si on prend comme r\u00e9f\u00e9rence les 15,5 milliards d\u2019euros de surco\u00fbt des OATi en 2022, une proportion significative de cette charge aurait \u00e9t\u00e9 \u00e9vit\u00e9e si des OAT classiques avaient \u00e9t\u00e9 \u00e9mises \u00e0 la place. En supposant que l\u2019inflation se stabilise autour de 5\u00a0% en 2024, le co\u00fbt des OATi pourrait \u00eatre encore sup\u00e9rieur \u00e0 10 milliards d\u2019euros par an.\nEn cons\u00e9quence du gouffre financier que repr\u00e9sente le co\u00fbt des OATi pour l\u2019\u00c9tat, le pr\u00e9sent amendement pr\u00e9voit l\u2019interdiction progressive des OATi sous 5 ans."}