{"id": 1057, "name": "Projet de loi de finances pour 2025, n\u00b0\u00a0324", "url": "/dyn/17/amendements/0324A/AN/1057", "date": "2024-10-17", "status": "Rejet\u00e9", "proposed_by": [{"first_name": "Fr\u00e9d\u00e9ric", "last_name": "Falcon", "party": "Rassemblement National"}], "summary": "Alors que la r\u00e9duction du train de vie de l'Etat et la recherche de pistes s\u00e9rieuses d'\u00e9conomie doivent \u00eatre une priorit\u00e9, la question du maintien de l\u2019Agence nationale de l\u2019habitat doit \u00eatre pos\u00e9e. Les comp\u00e9tences et missions de l\u2019Agence nationale de l\u2019habitat doivent \u00eatre r\u00e9internalis\u00e9es, l\u2019Etat disposant de suffisamment de fonctionnaires comp\u00e9tents sans avoir \u00e0 recourir \u00e0 des interm\u00e9diaires.\nIl appara\u00eet donc que le b\u00e9n\u00e9fice des recettes de la mise aux ench\u00e8res des quotas carbone pr\u00e9vus dans le pr\u00e9sent PLF pour financer l\u2019Agence nationale de l\u2019habitat seraient plus utiles ailleurs, ou simplement pour participer \u00e0 la r\u00e9duction du d\u00e9ficit."}