{"id": 33, "name": "Texte de la commission  sur la proposition de loi, modifi\u00e9e par le S\u00e9nat, visant \u00e0 harmoniser le mode de scrutin aux \u00e9lections municipales afin de garantir la vitalit\u00e9 d\u00e9mocratique, la coh\u00e9sion municipale et la parit\u00e9 (n\u00b01105)., n\u00b0\u00a01245-A0", "url": "/dyn/17/amendements/1245/AN/33", "date": "2025-04-03", "status": "Rejet\u00e9", "proposed_by": [{"first_name": "Nicolas", "last_name": "Dragon", "party": "Rassemblement National"}], "summary": "Amendement de repli.Pour les communes de moins de 1000 habitants situ\u00e9es en milieu rural, il est impossible de respecter les m\u00eames dispositions sp\u00e9ciales applicables aux communes de 1000 habitants et plus, notamment en ce qui concerne la d\u00e9claration de candidatures.En effet, imposer une parit\u00e9 alternant homme et femme sur les listes \u00e9lectorales est difficilement r\u00e9alisable dans la majorit\u00e9 de ces petites communes. Peu de personnes sont motiv\u00e9es et disponibles pour s\u2019engager dans la gestion des affaires communales, et les listes sont principalement compos\u00e9es de citoyens volontaires.Cela reviendrait donc \u00e0 emp\u00eacher les habitants volontaires de ces communes de moins de 1000 habitants d\u2019administrer leur commune, auquel ils sont profond\u00e9ment attach\u00e9s."}