{"id": 4093, "name": "Projet de loi de finances pour 2026, n\u00b0\u00a01906", "url": "/dyn/17/amendements/1906A/AN/4093", "date": "2025-11-21", "status": "Adopt\u00e9", "proposed_by": "Le Gouvernement", "summary": "Le pr\u00e9sent amendement tend \u00e0 porter de 300 \u00e0 600 millions d\u2019euros les sommes qui seront mobilis\u00e9es, en 2026, au titre du fonds de sauvegarde des d\u00e9partements, conform\u00e9ment \u00e0 l\u2019engagement du Premier ministre, en cl\u00f4ture des assises des d\u00e9partements de France.\nD\u2019apr\u00e8s les pr\u00e9visions sous-jacentes au projet de loi de finances, aucune reprise du produit de la taxe sur la valeur ajout\u00e9e (TVA) affect\u00e9e aux collectivit\u00e9s locales n\u2019aura lieu. Par cons\u00e9quent, l\u2019Etat abondera, sur sa part de TVA, le montant correspondant \u00e0 la diff\u00e9rence entre ce plafond de 600 millions et les sommes d\u2019ores-et-d\u00e9j\u00e0 affect\u00e9es \u00e0 ce m\u00eame fonds au titre des exercices 2024 et 2025."}